[
    {
        "id": 1,
        "cardId": 1,
        "type": "prepaidCard",
        "data": "220003000000003",
        "time": "2017-08-9T05:28:31+03:00",
        "sum": "2345"
    },
    {
        "id": 2,
        "cardId": 1,
        "type": "paymentMobile",
        "data": "+7(921)3333333",
        "time": "2017-08-8T06:28:31+03:00",
        "sum": "-25"
    },
    {
        "id": 3,
        "cardId": 1,
        "type": "card2Card",
        "data": "220003000000005",
        "time": "2017-08-25T13:28:31+03:00",
        "sum": "-174"
    },
    {
        "id": 4,
        "cardId": 1,
        "type": "prepaidCard",
        "data": "220003000000003",
        "time": "2017-08-25T12:28:31+03:00",
        "sum": "2345"
    },
    {
        "id": 5,
        "cardId": 1,
        "type": "paymentMobile",
        "data": "+7(921)3333333",
        "time": "2017-08-25T11:28:31+03:00",
        "sum": "-25"
    },
    {
        "id": 6,
        "cardId": 1,
        "type": "card2Card",
        "data": "220003000000005",
        "time": "2017-08-25T13:29:31+03:00",
        "sum": "-174"
    },
    {
        "id": 7,
        "cardId": 1,
        "type": "card2Card",
        "data": "220003000000005",
        "time": "2017-08-25T13:28:35+03:00",
        "sum": "-174"
    },
    {
        "id": 8,
        "cardId": 2,
        "type": "prepaidCard",
        "data": "220003000000003",
        "time": "2017-08-25T13:28:31+03:00",
        "sum": "2345"
    },
    {
        "id": 9,
        "cardId": 2,
        "type": "paymentMobile",
        "data": "+7(921)3333333",
        "time": "2017-08-25T13:28:31+03:00",
        "sum": "-25"
    },
    {
        "id": 10,
        "cardId": 2,
        "type": "card2Card",
        "data": "220003000000005",
        "time": "2017-08-25T13:28:31+03:00",
        "sum": "-174"
    },
    {
        "id": 11,
        "cardId": 2,
        "type": "prepaidCard",
        "data": "220003000000003",
        "time": "2017-08-25T13:28:31+03:00",
        "sum": "2345"
    },
    {
        "id": 12,
        "cardId": 2,
        "type": "paymentMobile",
        "data": "+7(921)3333333",
        "time": "2017-08-25T13:28:31+03:00",
        "sum": "-25"
    },
    {
        "id": 13,
        "cardId": 2,
        "type": "card2Card",
        "data": "220003000000005",
        "time": "2017-08-25T13:28:31+03:00",
        "sum": "-174"
    },
    {
        "id": 14,
        "cardId": 3,
        "type": "prepaidCard",
        "data": "220003000000003",
        "time": "2017-08-25T13:28:31+03:00",
        "sum": "2345"
    },
    {
        "id": 15,
        "cardId": 3,
        "type": "paymentMobile",
        "data": "+7(921)3333333",
        "time": "2017-08-25T13:28:31+03:00",
        "sum": "-25"
    },
    {
        "id": 16,
        "cardId": 4,
        "type": "prepaidCard",
        "data": "220003000000003",
        "time": "2017-08-25T13:28:31+03:00",
        "sum": "2345"
    },
    {
        "id": 17,
        "cardId": 4,
        "type": "paymentMobile",
        "data": "+7(921)3333333",
        "time": "2017-08-25T13:28:31+03:00",
        "sum": "-25"
    },
    {
        "id": 18,
        "cardId": 4,
        "type": "card2Card",
        "data": "220003000000005",
        "time": "2017-08-25T13:28:31+03:00",
        "sum": "-174"
    },
    {
        "id": 19,
        "cardId": 4,
        "type": "prepaidCard",
        "data": "220003000000003",
        "time": "2017-08-25T13:28:31+03:00",
        "sum": "2345"
    },
    {
        "id": 20,
        "cardId": 4,
        "type": "paymentMobile",
        "data": "+7(921)3333333",
        "time": "2017-08-25T13:28:31+03:00",
        "sum": "-25"
    },
    {
        "id": 21,
        "cardId": 4,
        "type": "card2Card",
        "data": "220003000000005",
        "time": "2017-08-25T13:28:31+03:00",
        "sum": "-174"
    },
    {
        "id": 22,
        "time": "2017-10-11T20:15:05.598Z",
        "cardId": 1,
        "type": "paymentMobile",
        "data": "+79218908064",
        "sum": -43
    },
    {
        "id": 23,
        "time": "2017-10-11T20:58:20.521Z",
        "cardId": 1,
        "type": "paymentMobile",
        "data": "+79218908064",
        "sum": -57
    },
    {
        "id": 24,
        "time": "2017-10-11T21:18:14.479Z",
        "cardId": 1,
        "type": "paymentMobile",
        "data": "+79218908064",
        "sum": -28
    },
    {
        "id": 25,
        "time": "2017-10-12T07:30:08.620Z",
        "cardId": 1,
        "type": "paymentMobile",
        "data": "+79218908064",
        "sum": -13
    },
    {
        "id": 26,
        "time": "2017-10-12T07:30:41.940Z",
        "cardId": 1,
        "type": "paymentMobile",
        "data": "+79218908064",
        "sum": -4
    },
    {
        "id": 27,
        "time": "2017-10-12T07:31:15.466Z",
        "cardId": 1,
        "type": "paymentMobile",
        "data": "+79218908064",
        "sum": -4
    },
    {
        "id": 28,
        "time": "2017-10-12T07:31:25.127Z",
        "cardId": 1,
        "type": "paymentMobile",
        "data": "+79218908064",
        "sum": -13
    }
]